{"mc2582":{"replay":"0000.json","stats":{"damageDealt":249,"statuesDestroyed":0}},"dp766":{"replay":"0001.json","stats":{"damageDealt":105.5,"statuesDestroyed":0}},"th702":{"replay":"0002.json","stats":{"damageDealt":24,"statuesDestroyed":2}},"amb311":{"replay":"0003.json","stats":{"damageDealt":0,"statuesDestroyed":0}},"tl621":{"replay":"0004.json","stats":{"damageDealt":30,"statuesDestroyed":1}},"ky355":{"replay":"0005.json","stats":{"damageDealt":4,"statuesDestroyed":0}},"jm2675":{"replay":"0006.json","stats":{"damageDealt":13,"statuesDestroyed":1}},"jl2395":{"replay":"0008.json","stats":{"damageDealt":25,"statuesDestroyed":0}},"zz586":{"replay":"0009.json","stats":{"damageDealt":21,"statuesDestroyed":0}},"esc58":{"replay":"0010.json","stats":{"damageDealt":22,"statuesDestroyed":2}},"ag2384":{"replay":"0011.json","stats":{"damageDealt":3,"statuesDestroyed":1}},"zf275":{"replay":"0012.json","stats":{"damageDealt":10.5,"statuesDestroyed":1}},"la526":{"replay":"0013.json","stats":{"damageDealt":60,"statuesDestroyed":2}},"bmf30":{"replay":"0014.json","stats":{"damageDealt":39.5,"statuesDestroyed":2}},"rt615":{"replay":"0015.json","stats":{"damageDealt":0,"statuesDestroyed":0}},"ts936":{"replay":"0016.json","stats":{"damageDealt":258,"statuesDestroyed":0}},"jt899":{"replay":"0017.json","stats":{"damageDealt":228,"statuesDestroyed":1}},"may35":{"replay":"0018.json","stats":{"damageDealt":160,"statuesDestroyed":0}},"sg2121":{"replay":"0019.json","stats":{"damageDealt":16,"statuesDestroyed":1}},"mc2462":{"replay":"0020.json","stats":{"damageDealt":40.5,"statuesDestroyed":1}},"lt599":{"replay":"0021.json","stats":{"damageDealt":54,"statuesDestroyed":0}},"dk729":{"replay":"0022.json","stats":{"damageDealt":112.5,"statuesDestroyed":0}},"pd531":{"replay":"0023.json","stats":{"damageDealt":80,"statuesDestroyed":1}},"sns45":{"replay":"0024.json","stats":{"damageDealt":105,"statuesDestroyed":1}},"asl63":{"replay":"0025.json","stats":{"damageDealt":123,"statuesDestroyed":0}},"ok333":{"replay":"0026.json","stats":{"damageDealt":526,"statuesDestroyed":3}},"bjc75":{"replay":"0027.json","stats":{"damageDealt":0,"statuesDestroyed":0}},"js2944":{"replay":"0028.json","stats":{"damageDealt":33,"statuesDestroyed":0}},"ng538":{"replay":"0029.json","stats":{"damageDealt":127,"statuesDestroyed":3}},"av733":{"replay":"0030.json","stats":{"damageDealt":12,"statuesDestroyed":1}},"kzl21":{"replay":"0031.json","stats":{"damageDealt":0,"statuesDestroyed":0}},"kob22":{"replay":"0032.json","stats":{"damageDealt":238,"statuesDestroyed":0}},"ac2620":{"replay":"0033.json","stats":{"damageDealt":21,"statuesDestroyed":2}},"ys648":{"replay":"0034.json","stats":{"damageDealt":70,"statuesDestroyed":0}},"ur233":{"replay":"0035.json","stats":{"damageDealt":104,"statuesDestroyed":0}},"cf600":{"replay":"0036.json","stats":{"damageDealt":126,"statuesDestroyed":1}},"ss3083":{"replay":"0037.json","stats":{"damageDealt":31,"statuesDestroyed":2}},"cl982":{"replay":"0038.json","stats":{"damageDealt":156,"statuesDestroyed":1}},"wc376":{"replay":"0039.json","stats":{"damageDealt":268,"statuesDestroyed":0}},"arp96":{"replay":"0040.json","stats":{"damageDealt":99,"statuesDestroyed":3}},"kh844":{"replay":"0041.json","stats":{"damageDealt":32.5,"statuesDestroyed":0}},"bew34":{"replay":"0042.json","stats":{"damageDealt":0,"statuesDestroyed":0}},"bdt29":{"replay":"0043.json","stats":{"damageDealt":51,"statuesDestroyed":2}},"mmd45":{"replay":"0044.json","stats":{"damageDealt":49.5,"statuesDestroyed":1}},"chw63":{"replay":"0045.json","stats":{"damageDealt":74,"statuesDestroyed":1}}}